{
    "711350": "Boetsja",
    "698929": "Novi Petrivtsi",
    "2020698": "Lozovaya",
    "697106": "Plesetske",
    "483826": "Tekstil\u2019shchiki",
    "702278": "Buhas",
    "702657": "Luhanska",
    "686858": "Zolotiiv",
    "700569": "Mykolayiv",
    "712508": "Bilozerka",
    "8516359": "Markhalivka",
    "686946": "Mariupol-Port",
    "700568": "Mykolaiv",
    "697287": "Petrovsky District",
    "704901": "Korosten",
    "550558": "Charkov",
    "696677": "Polohy",
    "707244": "Kakhovka",
    "709716": "Donetska",
    "709929": "Dnipropetrovsk",
    "687699": "Zaporizhzhya",
    "703446": "Kyiv",
    "9291559": "Imeni Stepana Bandery",
    "687700": "Zaporizhzhya",
    "689559": "Vinnytsya",
    "709276": "Enerhodar",
    "707896": "Huliaipole",
    "706448": "Cherson",
    "705505": "Kochubiivka",
    "686967": "Zjytomyr",
    "6722148": "Saltivka",
    "707565": "Irpin",
    "703448": "Kyiv",
    "704204": "Lyman",
    "696280": "Sartana",
    "706442": "Cherson",
    "687557": "Zatoka",
    "690165": "Velyki Kopani",
    "10323759": "Cheremushky",
    "710734": "Chernihivska",
    "711719": "Velykyi Zholudsk",
    "616743": "Druzhkivka",
    "713174": "Bachmoet",
    "6722150": "Pavlove Pole",
    "687495": "Zavorychi",
    "698738": "Odessa",
    "691999": "Sievierodonetsk",
    "693468": "Slovjansk",
    "699311": "Novopskov",
    "700051": "Nikopol",
    "703428": "Ladyzhyn",
    "706483": "Charkov",
    "710931": "Chaplino",
    "687149": "Zhykhar",
    "9030864": "Druzhkivka City Council",
    "691743": "Telychka",
    "697576": "Pervomaiskyi",
    "702972": "Lysychansk",
    "10323754": "Myrnyi",
    "709930": "Dnjepropetrovsk",
    "705104": "Kostiantynivka",
    "8519950": "Novosilky",
    "696563": "Popasne",
    "707489": "Ivankiv",
    "1281789": "Bay of Bengal",
    "698770": "Otsjakiv",
    "9113971": "Krasnyi Horodok",
    "708251": "Hostomel",
    "1525173": "Bol\u2019shoy \u012azyum",
    "811210": "Artemovskiy",
    "713787": "Adamivka",
    "687640": "Zarech\u2019ye",
    "813226": "Dovhenke",
    "696643": "Poltava",
    "548408": "Kirov",
    "8280075": "Sumy",
    "692196": "Soemy",
    "688860": "Voznesensk",
    "712451": "Berdyansk",
    "7525990": "Yuzhnoukrayinsk",
    "698428": "Orikhiv",
    "492094": "Slavyansk-na-Kubani",
    "703656": "Kupiansk",
    "693065": "Sotsmisto",
    "2121366": "Shakht\u00ebrskiy",
    "702549": "Lvivska",
    "699706": "Novooleksiyivka",
    "695274": "Rubizhne",
    "560116": "Gorenka",
    "693577": "Svyatohirsk",
    "692606": "Stepanivka",
    "706426": "Khitrovka",
    "545012": "Ozero Korabel\u2019noye",
    "692087": "Svitlovodsk",
    "697302": "Petrovskiy",
    "689198": "Volnovakha",
    "686906": "Znob Novhorodske",
    "713749": "Okhtyrka",
    "9113130": "Lastochkyne",
    "713122": "Avdiivka",
    "690269": "Velyka Danylivka",
    "710735": "Tsjernihiv",
    "9112184": "Hnativka",
    "705729": "Kyianytsia",
    "710098": "Derhachi",
    "710266": "Stantsiia Darivka",
    "3446158": "C\u00f3rrego das Tr\u00eas Barras",
    "11078484": "Kryvyy Rih",
    "691355": "Toshkivka",
    "710467": "Chikhirovo",
    "6723024": "Pivnichna Saltivka",
    "689138": "Volokhiv Yar",
    "697488": "Pisochyn",
    "697803": "Pechenihy",
    "470287": "Vyshgorod",
    "708784": "Hlevakha",
    "699339": "Novoplatonivka",
    "690688": "Uman",
    "806311": "Chaikivka",
    "698131": "Ovruch",
    "695716": "Rozumivka",
    "686895": "Zolochiv",
    "709399": "Dvorichna",
    "698286": "Osnova",
    "704508": "Kramatorsk",
    "705125": "Kinski Rozdory",
    "8516166": "Moshchun",
    "11776362": "Demiyevka",
    "701404": "Melitopol",
    "704147": "Krementsjoek",
    "706369": "Khmelnytskyi",
    "707753": "Horlivka",
    "812636": "Kolontayevka",
    "704191": "Vozdvyzhenka",
    "709354": "Toretsk",
    "6723018": "Shatylivka",
    "692248": "Stepnohirsk",
    "694363": "Shandryholove",
    "701845": "Mar'yinka",
    "11151337": "Volodymyrivske",
    "487193": "Stremoukhovo-Bobrik",
    "703625": "Kuren\u00ebvka",
    "711390": "Brovary",
    "705782": "Kyselivka",
    "690823": "Vuhledar",
    "806307": "Karavan",
    "702658": "Loehansk",
    "709718": "Donets Basin",
    "711592": "Borozenske",
    "1512052": "Akhtyrka",
    "695592": "Rivnenska",
    "709717": "Donetsk",
    "710514": "Oskil",
    "705598": "Klyuchevaya",
    "710374": "Chuhuiv",
    "713716": "Alchevsk",
    "474372": "Verkhoshizhemskiy Rayon",
    "698758": "Ocheretyne",
    "812732": "Zalyutino",
    "706566": "Kozatske",
    "803770": "Vetka",
    "688373": "Jasinoevata",
    "713245": "Apostolove",
    "9113996": "Druzhkivske",
    "697492": "Pisky-Radkivski",
    "707898": "Hulyaypole",
    "692703": "Staryi Saltiv",
    "701347": "Merefa",
    "692975": "Kadiyivka",
    "9113067": "Vesele",
    "695980": "Pisky-Richytski",
    "813242": "Radkivka",
    "790758": "Gatnje",
    "689304": "Vovchansk",
    "11125114": "Mandrykivka",
    "698107": "Ozerne",
    "711741": "Kyyiv District",
    "707292": "Izium",
    "9983718": "Cheremushky",
    "702116": "Malyn",
    "711635": "Borodianka",
    "601323": "Q\u016dnghirot",
    "462709": "Zhuravl\u00ebvka",
    "695357": "Kurakhove",
    "9873223": "Zymivnyk",
    "696566": "Popasna",
    "695094": "Rutchenkove",
    "692093": "Svetlodarsk",
    "9873202": "Korabeliv",
    "9030979": "Vuhledar City Council",
    "12324213": "Berkovets",
    "2123614": "Makarov",
    "688555": "Yakovlivka",
    "6722153": "Ivanivka",
    "712260": "Beryslav",
    "11778464": "Borshchahivka",
    "699839": "Nova Kakhovka",
    "688956": "Vorzel",
    "697706": "Peremoha",
    "691084": "Tsyrkuny",
    "711513": "Boiaro-Lezhachi",
    "690235": "Velyka Vilshanytsia",
    "696653": "Polovynkyne",
    "711894": "Bohodukhiv",
    "698408": "Orikhiv Raion",
    "710791": "Tsjerkasy",
    "1510006": "Blagodatnoye",
    "696050": "Pushcha-Vodytsya",
    "708421": "Gorki",
    "9291670": "Postnykove",
    "691252": "Trostyanets Raion",
    "9114637": "Novotoshkivske",
    "463835": "Zelenodolsk",
    "696377": "Pozniaky",
    "8516292": "Hurivshchyna",
    "690412": "Vasylkiv",
    "9873216": "Tekstylnyi",
    "710915": "Chasiv Yar",
    "702236": "Mala Buzova",
    "12239425": "Dubov\u00eb",
    "807359": "Zavody Pervyye",
    "689906": "Verkhniy Rohachyk Raion",
    "690335": "Vasyshcheve",
    "810695": "Opytne",
    "712165": "Bila Tserkva",
    "701320": "Metolkine",
    "704393": "Krasnohorivka",
    "712193": "Bezruky",
    "712559": "Bilopillia",
    "700178": "Mykolayivka",
    "8693025": "Dnipro Raion",
    "703845": "Kryvy Rih",
    "548363": "Kirovskiy Rayon",
    "8282558": "Urochishche Cherkassy",
    "8519916": "Obolon",
    "11564322": "Oleshky",
    "8669030": "Mala Rohan",
    "712181": "Bezimenne",
    "709983": "Dmytrivka",
    "695895": "Radisnyy Sad",
    "706950": "Kamianets-Podilskyi",
    "690266": "Velyka Dymerka",
    "699658": "Novobohdanivka",
    "712631": "Bilichi",
    "7647238": "Khromove",
    "705720": "Kyinka",
    "694137": "Shevchenkove",
    "712501": "Belozyorskoye",
    "696464": "Posad-Pokrovske",
    "692832": "Starobilsk",
    "708295": "Horokhovatka",
    "710400": "Chortkiv",
    "707026": "Kamyanka-Dniprovska",
    "807534": "Budarky",
    "10323583": "Skhidnyi",
    "693193": "Solonka",
    "696010": "Putilovka",
    "1490475": "Svyatogorsk",
    "691735": "Temyrivka",
    "699148": "Novosirotino",
    "692016": "Svyatogorsk",
    "705962": "Trudivskyi",
    "9920356": "Vesele",
    "698614": "Olenivka",
    "701078": "Obolonskyi Raion",
    "708634": "Hoholiv",
    "711154": "Burhunka",
    "710793": "Cherkaske",
    "728782": "Nikopol",
    "8519820": "Chaiky",
    "687796": "Zaliznychne",
    "9113204": "Kruta Balka",
    "710334": "Dachnoye",
    "698740": "Odessa",
    "11125111": "Promin",
    "712934": "Balabyne",
    "811044": "Imeni Artema",
    "705871": "Kindiyka",
    "693379": "Snihurivka",
    "6269553": "Sv. Petar (unknown beach name)",
    "691705": "Irmino",
    "688347": "Yasna Poliana",
    "713304": "Antonivka",
    "8504779": "Kriukivschina",
    "704466": "Krasnaya Armiya",
    "697650": "Perevalsk",
    "706757": "Soledar",
    "2121476": "Zaliv Schast\u2019ya",
    "695930": "Radens\u2019k",
    "699753": "Novhorod-Siverskyi",
    "12500938": "Oleksiivka",
    "700119": "Mykolaivka",
    "11110974": "Michurina",
    "8670023": "Kotliary",
    "686883": "Zolota Balka",
    "694992": "Rzhyshchiv",
    "704138": "Kreminna",
    "691222": "Kostyantynivka",
    "583028": "Aleksandrovskaya Dacha",
    "689180": "Vilnyansk Raion",
    "9113823": "Pivnichnyi",
    "703014": "Lipovaya Rosheha",
    "713068": "Pryazovske",
    "813046": "Mykilske",
    "686867": "Zolote",
    "699217": "Novoselivka",
    "702596": "Lukianivske",
    "1491202": "Spartak",
    "702220": "Mala Kardashynka",
    "702801": "Ivanivske",
    "713120": "Avdiivka",
    "709584": "Druzhba",
    "713685": "Oleksandrivka",
    "689405": "Volodymyrivka",
    "11557927": "Zelenyi Hai",
    "689548": "Vynohradne",
    "713259": "Antratsyt",
    "694423": "Sebastopol",
    "697898": "Pavlivka",
    "702423": "Liubomyrivka",
    "701561": "Mayaky",
    "706945": "Komyshany",
    "699193": "Novoselivka Druha",
    "713273": "Antonivka",
    "712450": "Stantsiia Berdiansk",
    "698836": "Nyrkove",
    "701822": "Marioepol",
    "687071": "Bohdanivske",
    "702320": "Makiivka",
    "9030870": "Bakhmut Municipality",
    "820638": "Urochishche Mar\u2019inka",
    "6724780": "Hlyboke",
    "696367": "Pravdyne",
    "709940": "Dnipryany",
    "694725": "Shchastia",
    "710715": "Chornobaivka",
    "712077": "Blahovishchenka",
    "700566": "Mylove",
    "711489": "Zaliznychne",
    "697974": "Makariv Yar",
    "9116876": "Zmiivka",
    "696218": "Pryvillia",
    "694076": "Shypylivka",
    "690424": "Vasylenkove",
    "687469": "Zaitseve",
    "698164": "Odradivka",
    "708599": "Hola Prystan Raion",
    "703484": "Kuzemivka",
    "702563": "Lutuhyne",
    "2019584": "Myla",
    "702073": "Malokakhovka",
    "707196": "Kalynove",
    "10349699": "Lukashivka",
    "688723": "Vyshhorod",
    "688841": "Vrubivka",
    "689900": "Verkhnotoretske",
    "610612": "Aqtau",
    "707307": "Izmaylovka",
    "692810": "Staromykhailivka",
    "9113824": "Dubovo-Vasylivka",
    "699473": "Novomaiorske",
    "686818": "Zuhres",
    "712091": "Blahodatne",
    "697613": "Manhush",
    "686810": "Zuivka",
    "2983543": "Rilhac-Lastours",
    "692480": "Urochishche Stoyanka",
    "688557": "Yakovlivka",
    "487289": "Strelech\u2019ya Polyana",
    "710229": "Debaltseve",
    "707352": "Ivanivka Raion",
    "703633": "Kurdiumivka",
    "707464": "Ivanopillia",
    "691469": "Tokmak",
    "692102": "Svesa",
    "688089": "Yuvileine",
    "9114314": "Malokostiantynivka",
    "10026211": "Dibrova Artsyzka",
    "812882": "Kolisnyky",
    "811160": "Nova Hnylytsia",
    "688040": "Yur'yivka",
    "713481": "Andriivka",
    "829794": "Prydniprovske",
    "710227": "Dubivka",
    "8142686": "Ozera Dardan-Kel\u2019",
    "692916": "Stara Bohdanivka",
    "708141": "Hryanykivka",
    "712588": "Bilohorivka",
    "693306": "Stantsiia Vilniansk",
    "692592": "Stepanivka",
    "810370": "Ivanovka",
    "713535": "Oleshky Sands",
    "699635": "Novodarivka",
    "710547": "Chervonopopivka",
    "705390": "Kolomyichykha",
    "693635": "Skovorodynivka",
    "709671": "Dorozhnianka",
    "695561": "Rohan",
    "697561": "Pervomaiske",
    "8340953": "Darivka",
    "522527": "Neskuchne",
    "9112865": "Zirka",
    "699402": "Novomykolayivka Raion",
    "712989": "Zaporizhzhya-Kam'yans'ke",
    "707651": "Myrne",
    "707677": "Stantsiia Ilovaisk",
    "705666": "Klyshchiivka",
    "689891": "Verkhnye Vodyane",
    "705497": "Kodema",
    "712775": "Bashtanka",
    "707155": "Kalynivka",
    "692624": "Stelmakhivka",
    "695392": "Kutuzivka",
    "713261": "Antopil",
    "12129174": "Bile",
    "699105": "Kobzartsi",
    "691073": "Tsupivka",
    "692105": "Dovzhansk",
    "9133385": "Rozivka Raion",
    "710237": "Davydiv Brid",
    "690089": "Velyka Oleksandrivka Raion",
    "708199": "Hrakove",
    "696141": "Protopopivka",
    "702807": "Loskutivka",
    "712521": "Bilovods'k",
    "3058786": "Marianka",
    "699351": "Sadove",
    "697593": "Pervomaysk",
    "689006": "Voronove",
    "700698": "Mostishche",
    "807109": "Shopyne",
    "3057772": "\u0160ahy",
    "712911": "Balashivka",
    "9130027": "Velyka Bilozerka Raion",
    "702760": "Lozova",
    "709114": "Fontanka",
    "8516167": "Horenka",
    "690903": "Tiahynka",
    "9114125": "Ozarianivka",
    "698163": "Odradokamianka",
    "698660": "Tsjyryljanske",
    "710798": "Cherkaska Lozova",
    "692827": "Starobohdanivka",
    "692799": "Starosillya",
    "694029": "Shyroke",
    "689641": "Verbivka",
    "690230": "Velyka Pysarivka",
    "704343": "Krasnopillia",
    "12181875": "Novhorod-Siversky station",
    "695106": "Ruska Lozova",
    "709474": "Dibrivne",
    "694152": "Shevchenkove",
    "695379": "Rovenky",
    "711885": "Bohorodychne",
    "694468": "Serhiivka",
    "9114153": "Prydonetske",
    "703652": "Kupiansk-Vuzlovyi",
    "811544": "Spirne",
    "711757": "Velyki Prokhody",
    "9112922": "Novobakhmutivka",
    "697601": "Pershokostiantynivka",
    "711116": "Buryn",
    "706524": "Kertsj",
    "688105": "Yevpatoriya",
    "692536": "Stepove",
    "700058": "Mykilske",
    "11144947": "Soldats\u2019ke",
    "697995": "Paraskoviivka",
    "699038": "Novovodyane",
    "692206": "Sulyhivka",
    "711597": "Borivske",
    "701324": "Messarosh",
    "689910": "Verkhnekamenskoye",
    "7586180": "Zavody",
    "3058370": "Oravsk\u00e9 Vesel\u00e9",
    "691374": "Chystyakove",
    "703477": "Kuzmyno",
    "706947": "Kamyanske",
    "697234": "Pylypcha",
    "706934": "Komyshuvakha",
    "865729": "Tavriysk",
    "695779": "Rivnopil",
    "7891622": "Buriakivka",
    "699617": "Novodonetske",
    "703057": "Lyman Druhyi",
    "687134": "Rzhyshchiv",
    "11782187": "Lenske",
    "705408": "Kolodiazi",
    "7304585": "The Trafford Centre",
    "707756": "Dachne",
    "690193": "Velykyi Burluk",
    "696269": "Prypiat",
    "686956": "Zymohiria",
    "688533": "Jalta",
    "468196": "Katerynivka",
    "711453": "Brazhkivka",
    "704556": "Kozyn",
    "707679": "Ilovays\u2019k",
    "709604": "Dronivka",
    "711435": "Brylivka",
    "686890": "Zolotarivka",
    "711802": "Velyka Komyshuvakha",
    "9113126": "Mineralne",
    "3072895": "Kr\u00e1sn\u00e1 Hora",
    "8664602": "Khudoiarove",
    "703116": "Levkovychi",
    "693709": "Skadovsk",
    "693004": "Stepne",
    "686966": "Zhytomyrska",
    "686930": "Slangeneiland",
    "9114149": "Zabavne",
    "707070": "Kam'yanka",
    "708272": "Hirske",
    "544407": "Korsunka",
    "690288": "Velyka Oleksandrivka",
    "577798": "Ozero Bile",
    "694792": "Sarny",
    "9114062": "Borodoiarske",
    "7500507": "Urochishche Serebryanka",
    "686729": "Vasylivka",
    "703646": "Kurakhovo",
    "1518674": "Sverdlovka",
    "682674": "Karpaten",
    "699461": "Novomykhailivka",
    "697531": "Pishchanivka",
    "9112916": "Abakumova",
    "691606": "Terny",
    "703394": "Lantrativka",
    "708320": "Horodnia",
    "4922013": "Jay County",
    "713665": "Novooleksandrivka",
    "710033": "Dmytrivka",
    "6930327": "Slavoetytsj",
    "688499": "Yampil Raion",
    "709373": "Dymer",
    "9115061": "Novoselivske",
    "811268": "Zaboyshchik",
    "809782": "Avilovka",
    "688148": "Yenakiieve",
    "710269": "Darivka",
    "699641": "Novodanylivka",
    "706563": "Kozatske",
    "810396": "Dolomitne",
    "699677": "Novoaidar",
    "699445": "Novomoskovsk",
    "697414": "Petropavlivka Raion",
    "9114140": "Zaliznianske",
    "688845": "Vremivka",
    "811088": "Imeni Krupskoy",
    "700414": "Nauholne",
    "702221": "Mala Komyshuvakha",
    "9120300": "Chapaievka",
    "811859": "Synetskyi",
    "688500": "Yampolivka",
    "693586": "Slavne",
    "697698": "Peremozhne",
    "558972": "Grecheskiye Roty",
    "704352": "Krasnopillya",
    "708146": "Hremiach",
    "687237": "Zhdanivka",
    "704422": "Pokrovsk",
    "710930": "Chaplynka Raion",
    "709207": "Fedorivka",
    "706370": "Khmelnytskyi",
    "811857": "Yuzhnaya",
    "703862": "Crimean Peninsula",
    "690250": "Velyka Kostromka",
    "698006": "Panteleimonivka",
    "704202": "Khrustalnyi",
    "701975": "Mali Prokhody",
    "806511": "Verkhnia Rohanka",
    "703610": "Kurylivka",
    "708622": "Holykove",
    "711375": "Bruskynske",
    "701452": "Medvedivka",
    "10361695": "Shyroka Dolyna",
    "1486831": "Voskresenka",
    "689487": "Vyshneve",
    "693269": "Sokolohirne",
    "12149075": "Zelenopillya",
    "692722": "Staryi Karavan",
    "11494777": "Trypillya-Dniprov'ske",
    "712912": "Balashivka",
    "694114": "Shevelivka",
    "696227": "Fedorovka",
    "9115656": "Pidlisne",
    "712586": "Bilohirka",
    "709334": "Dzhankoi",
    "705135": "Konotop",
    "692808": "Staromlynivka",
    "692262": "Sukhodol",
    "8516135": "Zdvyzhivka",
    "811207": "Krasnopillia",
    "811724": "Pavlohrad",
    "693678": "Skybyn",
    "710359": "Chumakove",
    "691776": "Tavriiske",
    "709145": "Filatovka",
    "691358": "Torske",
    "8417087": "Peresypky",
    "698548": "Vilkhivka",
    "698799": "Oborotnivka",
    "8675489": "Novyi Korotych",
    "3285031": "Pobjeda",
    "724271": "Lomnick\u00fd \u0161t\u00edt",
    "625899": "Lozove",
    "712662": "Bila Hora",
    "699701": "Novooleksiivka",
    "10317855": "Pionerske",
    "697956": "Novopavlivka",
    "8563993": "Chervonohvardiiske",
    "11361456": "Chornomors Ke",
    "813333": "Yahidne",
    "713208": "Arkhanhelske",
    "690579": "Ustia-Zelene",
    "709248": "Fastiv",
    "698973": "Novozlatopil",
    "9872848": "Inzhenerne",
    "3044130": "Tarany",
    "696447": "Postolne",
    "5128581": "New York",
    "696943": "Pidhorodne",
    "693078": "Sosnove",
    "8232288": "Zaozerne",
    "701809": "Markeiev",
    "809786": "Stavky",
    "693026": "Spivakivka",
    "689280": "Vovchkiv",
    "11415248": "Blahodativka",
    "9114311": "Stepove",
    "702598": "Lukianivka",
    "711930": "Bohdanivka",
    "687652": "Zarichne",
    "699542": "Novoivanivka",
    "8391470": "Druzhne",
    "694266": "Sjtsjoerove",
    "710796": "Cherkaski Tyshky",
    "709872": "Bohoiavlenka",
    "707473": "Ivano-Darivka",
    "8516181": "Blystavytsia",
    "705186": "Kal'mius'ke",
    "7731601": "Havryshivka International Airport",
    "699058": "Novovasylivka",
    "8224441": "Mriia",
    "712590": "Bilohorodka",
    "696176": "Chelburda",
    "692785": "Starovirivka",
    "698781": "Obukhovychi",
    "10323823": "Miskyi Ostriv",
    "712641": "Bilenke",
    "693457": "Smila",
    "9115288": "Bakhmutske",
    "709614": "Drobysheve",
    "693236": "Soldatske",
    "10323593": "Naidonivka",
    "11557922": "Vasylky",
    "697138": "Pytomnyk",
    "712271": "Berezivka Raion",
    "693032": "Novopetrivka",
    "699610": "Novoekonomicheskoye",
    "699867": "Nova Dmytrivka",
    "693957": "Dolynka",
    "487033": "Stud\u00ebnok",
    "707700": "Illinka",
    "12524807": "Honcharivka",
    "711521": "Bovshev",
    "9983655": "Lymanchyk",
    "712411": "Berestove",
    "692118": "Svatove",
    "691313": "Trykhaty",
    "707149": "Dzherelne",
    "710557": "Kyrylivka",
    "831460": "Armiansk",
    "703925": "Kruta Balka",
    "699745": "Novookhtyrka",
    "703713": "Kulykivka",
    "9114632": "Tytove",
    "695731": "Rozdollia",
    "701377": "Milova",
    "695760": "Raihorodok",
    "693598": "Slatyne",
    "2968279": "Ville-sur-Yron",
    "698570": "Olyshivka",
    "710004": "Dmytrivka",
    "9114138": "Berkhivka",
    "709960": "Dniprorudne",
    "689372": "Vladyslavivka",
    "690078": "Velyka Lepetykha Raion",
    "703953": "Kruhlyk",
    "692713": "Staryi Krym",
    "691863": "Tarasivka",
    "699615": "Novodruzhesk",
    "693695": "Skarhivka",
    "713017": "Babyntsi",
    "687999": "Pivdenna Bukhta",
    "710353": "Chupakhivka",
    "696150": "Prosyana",
    "630673": "Zwarte Zee",
    "687406": "Zelena Dolyna",
    "9113068": "Lozivskyi",
    "704337": "Krasnorichenske",
    "696292": "Prymorsk",
    "704413": "Tavriys'ke",
    "693450": "Smile",
    "7025405": "Novoozyornoye",
    "707268": "Kachkarivka",
    "699477": "Novomaryivka",
    "706466": "Khartsyzk",
    "11816657": "Vyshneve",
    "9103931": "Ridne",
    "11014186": "Teplychne",
    "11128162": "Voykovo",
    "712147": "Bilogorshche",
    "697889": "Pavlohrad",
    "699130": "Novostepnoye",
    "695763": "Raihorodka",
    "706883": "Kapitanivka",
    "697075": "Ploshchanka",
    "701357": "Menkivka",
    "1510678": "Bayrak",
    "807802": "Steblianky",
    "705175": "Kindrashivka",
    "695697": "Richky",
    "700280": "Nesterianka",
    "806067": "Tymofiivka",
    "690277": "Velyka Blahovishchenka",
    "695830": "Rakivka",
    "711569": "Borshchova",
    "823477": "Lupareve",
    "699621": "Novodniprovka",
    "706016": "Petrivka",
    "9112905": "Molodets'ke",
    "693965": "Topolyne",
    "793657": "Malynivka",
    "10266789": "Doslidne",
    "701828": "Marinskyi Raion",
    "694403": "Siversk",
    "699674": "Novoazovsk Raion",
    "687815": "Zalissia",
    "691610": "Ternovi Pody",
    "687911": "Travneve",
    "712951": "Bakhtyn",
    "11886997": "Yats'kivka Starostyns'kyi Okruh",
    "689517": "Vyry",
    "698533": "Vilshana",
    "9115685": "Lysychanskyi",
    "11361448": "Skadovs\u2019k",
    "7039154": "Novofedorovka",
    "9873176": "Bilohrudove",
    "709900": "Dobropillia",
    "9113141": "Novoselivka",
    "706742": "Karmazynivka",
    "713743": "Yakymivka",
    "700405": "Shlyakhove",
    "694752": "Savyntsi",
    "698962": "Nove",
    "700842": "Molochne",
    "2960848": "Noordzee",
    "708115": "Hryhorivka",
    "5062275": "University of North Dakota",
    "691778": "Tavilzhanka",
    "709022": "Halytsynove",
    "11109814": "Prystan Kamenka-Dneprovskaia",
    "705809": "Holubivka",
    "700567": "Mykolayiv",
    "8061348": "Urochishche Lyubotin",
    "3184701": "Mirn\u00eb",
    "688983": "Voroshilovka",
    "713504": "Amvrosiivka",
    "691279": "Troitske",
    "706095": "Hlyboke",
    "806536": "Male Vesele",
    "697299": "Verbky-Osokorivka",
    "1493229": "Urochishche Sakko i Vantsetti",
    "7451078": "Urochishche Berestyanka",
    "729242": "Marinka",
    "707336": "Ivashky",
    "693778": "Synkivka",
    "699963": "Nyzhnia Duvanka",
    "9644097": "Kreminets",
    "806437": "Bobrivka",
    "701027": "Myronivskyi",
    "711240": "Buhaivka",
    "691568": "Levadne",
    "709755": "Dolyna",
    "694300": "Shcherbaky",
    "699253": "Novosilka",
    "689154": "Nikolske Raion",
    "8631806": "Krynychna",
    "712682": "Bekhtery",
    "9112915": "Nevelske",
    "713811": "Kamianka",
    "696425": "Potomkyne",
    "7730188": "Khmelnytskyi Airport",
    "707414": "Ivanivka",
    "700446": "Narodychi",
    "699769": "Nova Zburivka",
    "6300962": "Ivano-Frankivsk",
    "689297": "Vovchoiarivka",
    "702055": "Malotaranivka",
    "694382": "Shakhtarsk",
    "702379": "Liutizh",
    "11011095": "Zherebianky",
    "809181": "Dolgiy Yar",
    "688689": "Vysokopillya",
    "703520": "Kutsurub",
    "687745": "Zamistia",
    "692138": "Suvorove",
    "693381": "Snizhne",
    "689558": "Vinnytsya",
    "692829": "Starobesheve",
    "699027": "Novovoznesenske",
    "700813": "Monachynivka",
    "699887": "Nova Basan",
    "704439": "Krasna Talivka",
    "700302": "Shestakove",
    "694494": "Serebrianka",
    "712502": "Bilozerka Raion",
    "688252": "Yehorivka",
    "687130": "Zhytlivka",
    "9921490": "Tsukury",
    "8669661": "Peremoha",
    "712926": "Balakliia",
    "691780": "Stantsiia Tavriisk",
    "693210": "Solodke",
    "698532": "Vilshana",
    "688851": "Vidrodzhennia",
    "690076": "Velyka Mykhaylivka Raion",
    "8533069": "Yevpatoria Airport",
    "812962": "Dokuchaievske",
    "708884": "Bila Krynytsia",
    "708920": "Havronshchyna",
    "542333": "Krasnogvardeyskoye",
    "695734": "Rozdolivka",
    "695966": "Piatykhatky",
    "698584": "Olhynka",
    "695720": "Oleksandropil",
    "688444": "Yarmaki",
    "704881": "Korotych",
    "703317": "Lazurne",
    "1275642": "Bilashi",
    "6316252": "Kukhari",
    "696362": "Prechystivka",
    "709710": "Donetske",
    "809187": "Sanzharovka",
    "704678": "Kotovka",
    "707758": "Hloechiv",
    "707853": "Husarivka",
    "712643": "Bilenke",
    "708663": "Hnivan",
    "702231": "Mala Danylivka",
    "710435": "Chkalove",
    "704000": "Krolevets",
    "703875": "Krymky",
    "809822": "Baranykivka",
    "10193033": "Henichesk",
    "9113993": "Molokove",
    "7021031": "Voloshino",
    "826047": "Pavlivs'ke Kolino",
    "705015": "Kopyliv",
    "689584": "Vilnyansk",
    "706378": "Khmilnytsia",
    "687682": "Zaporizhzhia",
    "812802": "Podvirky",
    "692011": "Desnianka",
    "694281": "Shchotove",
    "713207": "Arkhanhelske",
    "709465": "Dudchany",
    "710940": "Slobozhanske",
    "12232591": "Ak-Chokrak",
    "689757": "Vesela Tarasivka",
    "8468751": "Novy Yar",
    "696329": "Prybirsk",
    "710550": "Krynychanske",
    "695884": "Radyanskaya Sloboda",
    "710180": "Demydiv",
    "697346": "Osinovo",
    "818106": "Barvinok",
    "702989": "Lyptsi",
    "703488": "Bilmak Raion",
    "704578": "Kozarovychi",
    "705753": "Kyslivka",
    "699033": "Novovorontsovka Raion",
    "811597": "Heivka",
    "702337": "Makariv",
    "689764": "Vesela Dolyna",
    "711187": "Bulavynivka",
    "9797145": "Storozheve",
    "711764": "Vinnytski Khutory",
    "699603": "Novofedorivka",
    "712787": "Baryshivka",
    "699096": "Novotroitske",
    "690075": "Velyka Novosilka Raion",
    "686891": "Zolotarivka",
    "8669641": "Zatyshshia",
    "11011094": "Mali Shcherbaky",
    "8669029": "Biskvitne",
    "807105": "Hoptivka",
    "700203": "Nykyforivka",
    "695585": "Rodakove",
    "508088": "Podoly",
    "702684": "Luhanske",
    "708330": "Horodnye",
    "8661591": "Dvorichne",
    "708926": "Havrylivka Druha",
    "703555": "Kushuhum",
    "695118": "Rusaniv",
    "702459": "Lyubymivka",
    "701855": "Marhanets",
    "699688": "Novohannivka",
    "711613": "Borovenky",
    "711984": "Bochany",
    "707459": "Ivanovka",
    "2017833": "Urochishche Pokrovka",
    "698415": "Ozero Orikhove",
    "711118": "Bur\u2019yanovka",
    "8648337": "Baranycheve",
    "810398": "Mar\u2019yanovka",
    "688130": "Yaremivka",
    "1858596": "Koza-ch\u014d",
    "692953": "Stanytsia Luhanska",
    "711961": "Bahate",
    "706587": "Kozacha Lopan",
    "688913": "Voievodivka",
    "811580": "Klokovo",
    "689896": "Verkhneye",
    "702661": "Urochyshche Luhove",
    "695266": "Rubtsi",
    "701068": "Myrna Dolyna",
    "811095": "Anninskiy",
    "710357": "Chumatske",
    "690655": "Urozhaine",
    "9642874": "Ahrobaza",
    "708949": "Hatyshche",
    "700066": "Mykilske",
    "696261": "Pryshyb",
    "700429": "Natalyne",
    "9113135": "Krasnohorivka",
    "708273": "Hirske",
    "809789": "Myrne",
    "688108": "Krasnosilske",
    "11876420": "Crimean Bridge",
    "694910": "Saki",
    "708704": "Hliadyn",
    "713544": "Oleksiievo-Druzhkivka",
    "811070": "Komsomolets",
    "702246": "Mala Bilozerka",
    "9113201": "Troitske",
    "704639": "Kovalivka",
    "699563": "Novohryhorivka",
    "699527": "Novokamianka",
    "696741": "Pokrovske Raion",
    "712262": "Berylivka",
    "12495271": "Nekrasivka",
    "9115670": "Topolivka",
    "711581": "Borshchova",
    "692553": "Stepne",
    "698379": "Orlivka",
    "6724233": "Sosnovyi Bir",
    "690835": "Vidnozhyne",
    "702781": "Lozne",
    "691947": "Talakivka",
    "10922499": "Black Sea Region",
    "693738": "Sytniaky",
    "8675044": "Pryvokzalne",
    "1499340": "Mariinka",
    "705852": "Azovske",
    "712794": "Barvinkove",
    "7021003": "Izumrudnoye",
    "8524496": "Zalissia",
    "712131": "Krynychne",
    "9869409": "Tavriiske",
    "710163": "Demianiv",
    "687539": "Zavodivka",
    "694053": "Shyrokyne",
    "614409": "Goedaoeta",
    "518333": "Novopokrovka",
    "10400165": "Chornomorsk SeaPort",
    "9112086": "Fedorivka",
    "696205": "Pryiutne",
    "9983758": "Lymanka",
    "10353227": "Inhulets",
    "1516593": "Zhezdi",
    "701380": "Miluvatka",
    "713163": "Artsyz",
    "693182": "Solontsi",
    "806829": "Mantsivka",
    "700671": "Motyzhyn",
    "705602": "Klymentove",
    "808604": "Karaichne",
    "706446": "Mys Khersones",
    "710368": "Chulakivka",
    "694208": "Pirogovo",
    "688961": "Vorozhba",
    "691790": "Tetyanivka",
    "702963": "Liskhimstroy",
    "710195": "Dementiivka",
    "1521351": "Kazygurt",
    "699525": "Novokarlivka",
    "536164": "Tsaritsyno",
    "709132": "Balkove",
    "690822": "Vuhlehirsk",
    "699100": "Novotroyitske",
    "687805": "Zalyman",
    "697273": "Petrivske",
    "695714": "Rozumivka",
    "699853": "Plavske",
    "811166": "Mali Krynky",
    "700487": "Nahirne",
    "704940": "Korobochkyne",
    "689531": "Vynohradove",
    "703769": "Tokarivka",
    "703114": "Levkivka",
    "3016959": "Frontenay-Rohan-Rohan",
    "688341": "Yasnohorodka",
    "699675": "Novoazovs'k",
    "697821": "Zorivka",
    "706914": "Komysh-Zorya",
    "4863123": "KTIV-TV (Sioux City)",
    "702896": "Lobacheve",
    "812913": "Petrenkov",
    "711369": "Brianka",
    "701243": "Mikhaylovka",
    "8072118": "Gora Perekop",
    "8677642": "Rakivka",
    "10871037": "Pershozvanivka",
    "698950": "Novyi Bykiv",
    "692280": "Sukha Kamianka",
    "713209": "Arkhanhelska Sloboda",
    "811091": "Sadovyy",
    "8516155": "Ozera",
    "9115363": "Novoluhanske",
    "695101": "Ruski Tyshky",
    "699657": "Novobohdanivka",
    "810215": "Imeni Kalinina",
    "688068": "Yurchenkove",
    "699324": "Novopil",
    "712569": "Bilokurakyne",
    "9806345": "Novhorod-Sivers\u2019ka Mis\u2019krada",
    "698861": "Novyi Svit",
    "6724214": "Pytomnyk",
    "8504949": "Vasyl'evsky Ostrov",
    "699554": "Novohuivynske",
    "700388": "Nechaieve",
    "809450": "Perekop",
    "689139": "Volokhivka",
    "697614": "Pershotravneve",
    "704403": "Sorokyne",
    "689802": "Virnopillia",
    "688563": "Yakovenkove",
    "700012": "Nyzhni Sirohozy Raion",
    "696333": "Pryazovske Raion",
    "692449": "Striletska Bukhta",
    "1501305": "Kurilovka",
    "811074": "Kashanovka",
    "709046": "Halahanivka",
    "690840": "Raiske",
    "696689": "Politotdel\u2019skiy",
    "697653": "Pereval'noye",
    "1502650": "Konovalova",
    "9869178": "Klapaia",
    "707227": "Kalanchak Raion",
    "9869174": "Parysheve",
    "9124671": "Stukalova Balka",
    "694062": "Shyroka Balka",
    "690771": "Ukrainsk",
    "699024": "Novoiakovlivka",
    "705675": "Klynove",
    "687790": "Zaliznyy Port",
    "9916140": "Lvove",
    "699609": "Novoekonomichne",
    "709954": "Dniprovka",
    "699585": "Novohrednieve",
    "712574": "Bilokopytove",
    "11822749": "Zdorivka",
    "704186": "Myrne",
    "811211": "Striapivka",
    "688687": "Vysokopillia",
    "707245": "Kairy",
    "11902779": "Vilnius Quarter",
    "6723055": "Metalivka",
    "699650": "Novyy Buh Raion",
    "630063": "Bobryk",
    "707326": "Iverske",
    "707547": "Ishchenka",
    "706253": "Khotin",
    "692890": "Stara Krasnianka",
    "701462": "Midna Ruda",
    "1494226": "Preobrazhenka",
    "694677": "Selydove",
    "810696": "Ivanhrad",
    "809473": "Kalynivske",
    "8019862": "Karachuny",
    "620367": "Velikaya Dolya",
    "694702": "Volcheyarovka Nomer Pervyy",
    "693784": "Synychyne",
    "705069": "Kvitneve",
    "701021": "Myropillia",
    "8149610": "Korobky",
    "572243": "Bordyanka",
    "701853": "Molodizhne",
    "693754": "Syrotyne",
    "701588": "Matviivka",
    "8403095": "Velyka Doroha",
    "3697211": "El Ra\u00edz",
    "713588": "Oleksandrivsk",
    "711896": "Bohodarove",
    "11078245": "Zelenyi Hai",
    "701491": "Mayskoye",
    "570864": "Burchak",
    "698562": "Vilkhuvatka",
    "691092": "Levadne",
    "699964": "Nyzhnoderevechka",
    "703497": "Viazivka",
    "479347": "Ukrainka",
    "712755": "Batal\u2019noye",
    "712718": "Bairak",
    "690648": "Usatove",
    "703676": "Kunie",
    "12156788": "Karavelove",
    "699363": "Novopetrykivka",
    "708760": "Hlynske",
    "710894": "Checheleve",
    "9116779": "Vil\u2019khivka",
    "2441185": "Mayaki Kouara",
    "7503148": "Tretiaky",
    "698413": "Orikhovo-Vasylivka",
    "708400": "Hornostayivka Raion",
    "701034": "Myronivka",
    "9983721": "Arkadiia",
    "694986": "Sabivka",
    "6724144": "Shovkopliasy",
    "703052": "Liubymivka",
    "703055": "Lymany",
    "810623": "Nyzhnia Zhuravka",
    "701860": "Marfopil",
    "706886": "Kapytolivka",
    "712895": "Balky",
    "710571": "Chervone",
    "712967": "Bakhmach",
    "704368": "Krasnoliubetsk",
    "693517": "Sloboda-Viazivka",
    "705549": "Kniazivka",
    "703005": "Lypivka",
    "694193": "Shestovytsia",
    "688309": "Yats\u2019kivka",
    "9113800": "Brusivka",
    "713526": "Alisivka",
    "712120": "Bytytsia",
    "696151": "Prostore",
    "503854": "Pustosh\u2019 Prudyanka",
    "701327": "Mishkovo-Pohorilove",
    "698573": "Olhivka",
    "11503835": "Berkovets",
    "809276": "Reveyn",
    "691390": "Topilske",
    "709473": "Dibrivne",
    "699531": "Novokairy",
    "689759": "Vesela Hora",
    "688288": "Yavoriv",
    "710516": "Chervonyi Maiak",
    "1543207": "Ozero Sadok",
    "691037": "Oleshky",
    "697024": "Pobednoye",
    "696058": "Ozero Pulemetske",
    "708876": "Henichesk Raion",
    "688706": "Vyskryva",
    "700008": "Nyzhnie",
    "697233": "Pylypchatyne",
    "701607": "Matrosivka",
    "700829": "Molodohvardiisk",
    "8377081": "Voloshyne",
    "11782117": "Prybuz'ke",
    "699504": "Kostyrka",
    "9115723": "Verkhnii Tokmak Pershyi",
    "11012842": "Troiandy",
    "688345": "Yasnohirka",
    "691416": "Tomyna Balka",
    "710445": "Chystovodivka",
    "711815": "Velyka Buzova",
    "9921349": "Prystan Dnipriany",
    "708001": "Hrushivka",
    "711831": "Bolotnia",
    "696358": "Predmostnoye",
    "686896": "Zolochiv",
    "712200": "Bezliudivka",
    "710412": "Chonhar Peninsula",
    "699942": "Nizjyn",
    "582661": "Al\u00ebshki",
    "709808": "Dovhe",
    "9113501": "Mazanivka",
    "494448": "Shilova Balka",
    "706081": "Kalynivka",
    "710429": "Chkalovske",
    "702569": "Loetsk",
    "713117": "Avdotine",
    "697596": "Nevske",
    "694061": "Shyroka Balka",
    "702153": "Mala Tokmachka",
    "781440": "T\u00ebrnova e Madhe",
    "711854": "Bokove-Platove",
    "807104": "Kudiivka",
    "809778": "Sketevatyy",
    "461727": "Olenevka",
    "8217239": "Ozero Pishchane",
    "711669": "Boryslav",
    "711823": "Velyke Artakove",
    "709367": "Tarasovka",
    "690595": "Ustynivka Raion",
    "699497": "Novokrasnianka",
    "704793": "Tasunovo",
    "806446": "Imeni Frunze",
    "3239056": "Ob\u010dina Lo\u0161ka Dolina",
    "695441": "Rozkishne",
    "690310": "Vavylove",
    "703739": "Kulazhyntsi",
    "713256": "Promin",
    "711151": "Burkhanivka",
    "9114136": "Andriivka",
    "9114147": "Rudneve",
    "704114": "Khreshchenivka",
    "6724777": "Pletenivka",
    "691065": "Tsvitkove",
    "11510287": "Opytnoe Pole",
    "708761": "Hlynske",
    "10172822": "Aviatorske",
    "8648425": "Nova Tarasivka",
    "9116673": "Myronivske Vodoskhovyshche",
    "691639": "Ternuvate",
    "713176": "Zalizne"
}